gcloud_aio_core-0.7.2-py3.6-nspkg.pth
gcloud/aio/core/__init__.py
gcloud/aio/core/aio.py
gcloud/aio/core/astate.py
gcloud/aio/core/http.py
gcloud_aio_core-0.7.2.dist-info/DESCRIPTION.rst
gcloud_aio_core-0.7.2.dist-info/METADATA
gcloud_aio_core-0.7.2.dist-info/RECORD
gcloud_aio_core-0.7.2.dist-info/WHEEL
gcloud_aio_core-0.7.2.dist-info/metadata.json
gcloud_aio_core-0.7.2.dist-info/namespace_packages.txt
gcloud_aio_core-0.7.2.dist-info/top_level.txt
tests/unit/__init__.py
tests/unit/aio_test.py
tests/unit/astate_test.py
tests/unit/http_test.py
