Metadata-Version: 2.0
Name: gcloud-aio-core
Version: 0.7.2
Summary: Core Helpers for Asyncio Google Cloud Library
Home-page: https://github.com/talkiq/gcloud-aio
Author: TalkIQ
Author-email: engineering@talkiq.com
License: MIT License
Platform: Posix; MacOS X; Windows
Classifier: Development Status :: 4 - Beta
Classifier: Intended Audience :: Developers
Classifier: License :: OSI Approved :: MIT License
Classifier: Operating System :: OS Independent
Classifier: Programming Language :: Python :: 3
Classifier: Programming Language :: Python :: 3.6
Classifier: Topic :: Internet
Requires-Dist: aiohttp (<3.0.0,>=2.0.0)
Requires-Dist: asyncio-extras (<2.0.0,>=1.0.0)
Requires-Dist: ujson (<2.0.0,>=1.0.0)
